setup.py
sounddrizzle.py
SoundDrizzle.egg-info/PKG-INFO
SoundDrizzle.egg-info/SOURCES.txt
SoundDrizzle.egg-info/dependency_links.txt
SoundDrizzle.egg-info/entry_points.txt
SoundDrizzle.egg-info/requires.txt
SoundDrizzle.egg-info/top_level.txt