Metadata-Version: 1.1
Name: SoundDrizzle
Version: 1.0.1
Summary: An easy client to add SoundCloud tracks to your offline collection
Home-page: https://github.com/wonderb0lt/sounddrizzle
Author: Patrick Stegmann (aka. @wonderb0lt)
Author-email: code@patrick-stegmann.de
License: LICENSE
Platform: UNKNOWN
Classifier: Development Status :: 4 - Beta
Classifier: Environment :: Console
Classifier: License :: OSI Approved :: MIT License
Classifier: Operating System :: OS Independent
